torms_tedd28014/__init__.py
torms_tedd28014/torms_tedd28014.py
torms-1.1.1.dist-info/LICENSE
torms-1.1.1.dist-info/METADATA
torms-1.1.1.dist-info/WHEEL
torms-1.1.1.dist-info/top_level.txt
torms-1.1.1.dist-info/RECORD
