Metadata-Version: 2.1
Name: torms
Version: 1.1.1
Summary: Quickstarter for Tornado
Author: Tedd Saito
License: MIT License
License-File: LICENSE
Requires-Dist: Thread
